{
  "source": "TMDb (enrich)",
  "share": {
    "by_country_films": {
      "Argentina": {
        "Independents": 39,
        "Disney": 8,
        "Sony": 4,
        "Paramount": 3,
        "Universal/NBC": 1
      },
      "Uruguay": {
        "Independents": 40,
        "Disney": 8,
        "Sony": 4,
        "Paramount": 3
      },
      "Paraguay": {
        "Independents": 41,
        "Disney": 8,
        "Sony": 5,
        "Paramount": 1
      },
      "Chile": {
        "Independents": 34,
        "Disney": 8,
        "Sony": 6,
        "Universal/NBC": 4,
        "Paramount": 3
      },
      "Brazil": {
        "Independents": 38,
        "Sony": 10,
        "Universal/NBC": 5,
        "Paramount": 2
      },
      "Mexico": {
        "Independents": 31,
        "Sony": 10,
        "Universal/NBC": 6,
        "Disney": 4,
        "Paramount": 3,
        "Warner": 1
      },
      "Colombia": {
        "Independents": 38,
        "Disney": 8,
        "Sony": 5,
        "Universal/NBC": 3,
        "Warner": 1
      },
      "Peru": {
        "Independents": 31,
        "Sony": 7,
        "Disney": 5,
        "Universal/NBC": 2
      }
    },
    "by_country_tv": {
      "Argentina": {
        "Independents": 48,
        "Sony": 7
      },
      "Uruguay": {
        "Independents": 45,
        "Sony": 8,
        "Warner": 2
      },
      "Paraguay": {
        "Sony": 10,
        "Independents": 42,
        "Warner": 3
      },
      "Chile": {
        "Independents": 45,
        "Sony": 8,
        "Warner": 2
      },
      "Brazil": {
        "Sony": 10,
        "Independents": 43,
        "Warner": 2
      },
      "Mexico": {
        "Independents": 49,
        "Sony": 6
      },
      "Colombia": {
        "Independents": 46,
        "Sony": 9
      },
      "Peru": {
        "Independents": 42,
        "Sony": 9,
        "Warner": 3,
        "Paramount": 1
      }
    },
    "ultracine_ar_weeks_at_1": {},
    "ultracine_ar_espectadores": {},
    "mojo_us_gross": {
      "Disney": 77774000,
      "Independents": 78021056,
      "Universal/NBC": 12390000,
      "Warner": 2230000,
      "Sony": 1019
    },
    "ultracine_weekly_studio": []
  }
}